ksbrelease.py
PYTHONRELEASEKSB/__init__.py
PYTHONRELEASEKSB/ksbrelease.py
PYTHONRELEASEKSB-1.0.9.dist-info/METADATA
PYTHONRELEASEKSB-1.0.9.dist-info/WHEEL
PYTHONRELEASEKSB-1.0.9.dist-info/top_level.txt
PYTHONRELEASEKSB-1.0.9.dist-info/RECORD
